{
  "posts": [
    {
      "id": 1,
      "title": "json-server",
      "author": "typicode"
    },
    {
      "title": "json-server2",
      "author": "typicode",
      "id": 2
    },
    {
      "title": "json-server-edited3",
      "author": "typicode",
      "id": 3
    }
  ],
  "users": [
    {
      "id": 1,
      "name": "Chandrakant",
      "address": "Odisa"
    },
    {
      "id": 2,
      "name": "Prashant",
      "address": "Lucknow"
    }
  ],
  "todo": [
    {
      "isCompleted": false,
      "taskName": "Item4",
      "id": 4
    },
    {
      "isCompleted": false,
      "taskName": "Item5",
      "id": 5
    },
    {
      "isCompleted": false,
      "taskName": "item3",
      "id": 6
    },
    {
      "taskName": "Item6",
      "id": 7
    },
    {
      "isCompleted": false,
      "taskName": "Item7",
      "id": 8
    },
    {
      "isCompleted": false,
      "taskName": "Item8",
      "id": 9
    },
    {
      "isCompleted": false,
      "taskName": "asdasdfasfasdfsdfasdfasdf",
      "id": 10
    },
    {
      "isCompleted": false,
      "taskName": "asdf",
      "id": 11
    },
    {
      "isCompleted": false,
      "taskName": "asdasdf",
      "id": 12
    },
    {
      "isCompleted": false,
      "taskName": "asdasdf",
      "id": 13
    }
  ]
}